import_helpers
