Metadata-Version: 1.1
Name: import-helpers
Version: 0.1.1
Summary: Python import helpers
Home-page: https://github.com/mturilin/import_helpers
Author: mikhail.turilin
Author-email: mturilin@gmail.com
License: MIT
Platform: UNKNOWN
Classifier: Programming Language :: Python
